[
  {
    "full_name": "Knighthawk-Leo/Awesome_Python_Scripts",
    "stargazers_count": 2,
    "open_issues_count": 0,
    "forks_count": 0
  },
  {
    "full_name": "iAdityaNarayanT/secure-share",
    "stargazers_count": 1,
    "open_issues_count": 0,
    "forks_count": 1
  },
  {
    "full_name": "ntsd/zero-share",
    "stargazers_count": 65,
    "open_issues_count": 1,
    "forks_count": 5
  },
  {
    "full_name": "keploy/keploy",
    "stargazers_count": 2955,
    "open_issues_count": 159,
    "forks_count": 306
  },
  {
    "full_name": "vagabond-systems/forage-lyft-starter-repo",
    "stargazers_count": 108,
    "open_issues_count": 85,
    "forks_count": 2431
  },
  {
    "full_name": "riti2409/Resources-for-preparation-Of-Placements",
    "stargazers_count": 3016,
    "open_issues_count": 9,
    "forks_count": 801
  },
  {
    "full_name": "sajib1066/django-event-management",
    "stargazers_count": 104,
    "open_issues_count": 2,
    "forks_count": 55
  },
  {
    "full_name": "codewithrafiq/Social-Network-in-Django-and-Reactjs",
    "stargazers_count": 3,
    "open_issues_count": 0,
    "forks_count": 2
  },
  {
    "full_name": "fineanmol/Hacktoberfest2023",
    "stargazers_count": 1929,
    "open_issues_count": 3245,
    "forks_count": 7258
  },
  {
    "full_name": "ossamamehmood/Hacktoberfest",
    "stargazers_count": 1357,
    "open_issues_count": 2,
    "forks_count": 5409
  },
  {
    "full_name": "rohitg00/DevOpsCommunity",
    "stargazers_count": 548,
    "open_issues_count": 5,
    "forks_count": 127
  },
  {
    "full_name": "kubescape/kubescape",
    "stargazers_count": 9440,
    "open_issues_count": 57,
    "forks_count": 794
  },
  {
    "full_name": "bregman-arie/devops-exercises",
    "stargazers_count": 60483,
    "open_issues_count": 53,
    "forks_count": 13080
  },
  {
    "full_name": "in28minutes/devops-master-class",
    "stargazers_count": 1875,
    "open_issues_count": 11,
    "forks_count": 5281
  },
  {
    "full_name": "kubernetes/kubernetes",
    "stargazers_count": 104528,
    "open_issues_count": 2996,
    "forks_count": 38918
  }
]