[
  {
    "full_name": "Knighthawk-Leo/Awesome_Python_Scripts",
    "stargazers_count": 2,
    "open_issues_count": 0,
    "forks_count": 1
  },
  {
    "full_name": "iAdityaNarayanT/secure-share",
    "stargazers_count": 1,
    "open_issues_count": 0,
    "forks_count": 2
  },
  {
    "full_name": "ntsd/zero-share",
    "stargazers_count": 79,
    "open_issues_count": 1,
    "forks_count": 6
  },
  {
    "full_name": "keploy/keploy",
    "stargazers_count": 3787,
    "open_issues_count": 152,
    "forks_count": 419
  },
  {
    "full_name": "vagabond-systems/forage-lyft-starter-repo",
    "stargazers_count": 112,
    "open_issues_count": 88,
    "forks_count": 2504
  },
  {
    "full_name": "riti2409/Resources-for-preparation-Of-Placements",
    "stargazers_count": 3438,
    "open_issues_count": 10,
    "forks_count": 871
  },
  {
    "full_name": "sajib1066/django-event-management",
    "stargazers_count": 132,
    "open_issues_count": 6,
    "forks_count": 65
  },
  {
    "full_name": "codewithrafiq/Social-Network-in-Django-and-Reactjs",
    "stargazers_count": 3,
    "open_issues_count": 0,
    "forks_count": 2
  },
  {
    "full_name": "fineanmol/Hacktoberfest2024",
    "stargazers_count": 1854,
    "open_issues_count": 3069,
    "forks_count": 6852
  },
  {
    "full_name": "ossamamehmood/Hacktoberfest",
    "stargazers_count": 1296,
    "open_issues_count": 0,
    "forks_count": 5084
  },
  {
    "full_name": "rohitg00/DevOpsCommunity",
    "stargazers_count": 578,
    "open_issues_count": 5,
    "forks_count": 133
  },
  {
    "full_name": "kubescape/kubescape",
    "stargazers_count": 10022,
    "open_issues_count": 46,
    "forks_count": 834
  },
  {
    "full_name": "bregman-arie/devops-exercises",
    "stargazers_count": 65325,
    "open_issues_count": 32,
    "forks_count": 14530
  },
  {
    "full_name": "in28minutes/devops-master-class",
    "stargazers_count": 2212,
    "open_issues_count": 14,
    "forks_count": 5832
  },
  {
    "full_name": "kubernetes/kubernetes",
    "stargazers_count": 109051,
    "open_issues_count": 2574,
    "forks_count": 39069
  }
]